{
  "cli": {
    "version": ">= 3.5.2"
  },
  "build": {
    "local-dev": {
      "developmentClient": true,
      "distribution": "internal",
      "ios": {
        "resourceClass": "m-medium",
        "simulator": true
      }
    },
    "development": {
      "developmentClient": true,
      "distribution": "internal",
      "ios": {
        "resourceClass": "m-medium"
      }
    },
    "staging": {
      "distribution": "internal",
      "ios": {
        "resourceClass": "m-medium"
      }
    },
    "production": {
      "ios": {
        "resourceClass": "m-medium"
      }
    }
  },
  "submit": {
    "production": {}
  }
}
